asm_python.cpython-39-darwin.so
asm_python-1.0.dist-info/METADATA
asm_python-1.0.dist-info/WHEEL
asm_python-1.0.dist-info/top_level.txt
asm_python-1.0.dist-info/RECORD
