Metadata-Version: 2.1
Name: asm-python
Version: 1.0
Summary: A module that executes assembly code.
Home-page: UNKNOWN
Author: Bobby
License: UNKNOWN
Platform: UNKNOWN
